pyrion/__init__.py
pyrion/_bed12parser.cpython-310-darwin.so
pyrion/_bed12parser.pyi
pyrion/_chainparser.cpython-310-darwin.so
pyrion/_chainparser.pyi
pyrion/_faiparser.cpython-310-darwin.so
pyrion/_faiparser.pyi
pyrion/_fastaparser.cpython-310-darwin.so
pyrion/_fastaparser.pyi
pyrion/_gtfparser.cpython-310-darwin.so
pyrion/_gtfparser.pyi
pyrion/_narrowbedparser.cpython-310-darwin.so
pyrion/_narrowbedparser.pyi
pyrion/_version.py
pyrion/config.py
pyrion/constants.py
pyrion/core_types.py
pyrion/py.typed
pyrion/visualization.py
pyrion/core/__init__.py
pyrion/core/amino_acid_auxiliary.py
pyrion/core/amino_acid_sequences.py
pyrion/core/canonizer.py
pyrion/core/codons.py
pyrion/core/fai.py
pyrion/core/gene_data.py
pyrion/core/genes.py
pyrion/core/genes_auxiliary.py
pyrion/core/genome_alignment.py
pyrion/core/genome_alignment_auxiliary.py
pyrion/core/intervals.py
pyrion/core/intervals_auxiliary.py
pyrion/core/nucleotide_sequences.py
pyrion/core/sequences_auxiliary.py
pyrion/core/sequences_collection.py
pyrion/core/strand.py
pyrion/core/translation.py
pyrion/io/__init__.py
pyrion/io/bed.py
pyrion/io/chain.py
pyrion/io/fai.py
pyrion/io/fasta.py
pyrion/io/gene_data.py
pyrion/io/genepred.py
pyrion/io/gtf.py
pyrion/io/twobit.py
pyrion/misc/__init__.py
pyrion/misc/rna_basic_bpm.py
pyrion/ops/__init__.py
pyrion/ops/chain_serialization.py
pyrion/ops/chain_slicing.py
pyrion/ops/chains.py
pyrion/ops/data_consistency.py
pyrion/ops/entity_ops.py
pyrion/ops/genes.py
pyrion/ops/interval_collection_ops.py
pyrion/ops/interval_ops.py
pyrion/ops/interval_serialization.py
pyrion/ops/interval_slicing.py
pyrion/ops/interval_slicing_optimized.py
pyrion/ops/intervals.py
pyrion/ops/sequence_serialization.py
pyrion/ops/transcript_serialization.py
pyrion/ops/transcript_slicing.py
pyrion/ops/transformations.py
pyrion/utils/__init__.py
pyrion/utils/amino_acid_encoding.py
pyrion/utils/encoding.py
pyrion/utils/numpy_utils.py
pyrion-0.1.11.dist-info/licenses/LICENSE
pyrion-0.1.11.dist-info/METADATA
pyrion-0.1.11.dist-info/WHEEL
pyrion-0.1.11.dist-info/top_level.txt
pyrion-0.1.11.dist-info/RECORD
